reg2es/__init__.py
reg2es/models/ElasticsearchUtils.py
reg2es/models/Reg2es.py
reg2es/presenters/Reg2esPresenter.py
reg2es/presenters/Reg2jsonPresenter.py
reg2es/views/BaseView.py
reg2es/views/Reg2esView.py
reg2es/views/Reg2jsonView.py
reg2es-1.0.1.dist-info/entry_points.txt
reg2es-1.0.1.dist-info/LICENSE
reg2es-1.0.1.dist-info/WHEEL
reg2es-1.0.1.dist-info/METADATA
reg2es-1.0.1.dist-info/RECORD
