Metadata-Version: 2.1
Name: reg2es
Version: 1.0.1
Summary: A library for fast import of Windows NT Registry(REGF) into Elasticsearch.
Home-page: https://github.com/sumeshi/reg2es
License: MIT
Keywords: registry,elasticsearch,json
Author: sumeshi
Author-email: j15322sn@gmail.com
Requires-Python: >=3.7,<4.0
Classifier: License :: OSI Approved :: MIT License
Classifier: Programming Language :: Python :: 3
Classifier: Programming Language :: Python :: 3.7
Classifier: Programming Language :: Python :: 3.8
Requires-Dist: elasticsearch (>=7.7.1,<8.0.0)
Requires-Dist: importlib_metadata (>=4.6.1,<5.0.0)
Requires-Dist: libregf-python (>=20210615,<20210616)
Requires-Dist: orjson (>=3.6.0,<4.0.0)
Requires-Dist: tqdm (>=4.46.1,<5.0.0)
Requires-Dist: urllib3 (>=1.26.5,<2.0.0)
Project-URL: Repository, https://github.com/sumeshi/reg2es
